zrok/__init__.py
zrok/_version.py
zrok/access.py
zrok/decor.py
zrok/dialer.py
zrok/listener.py
zrok/model.py
zrok/overview.py
zrok/proxy.py
zrok/share.py
zrok/environment/__init__.py
zrok/environment/dirs.py
zrok/environment/root.py
zrok_build_debugging-0.0.10010.dist-info/METADATA
zrok_build_debugging-0.0.10010.dist-info/WHEEL
zrok_build_debugging-0.0.10010.dist-info/top_level.txt
zrok_build_debugging-0.0.10010.dist-info/RECORD
