Metadata-Version: 2.2
Name: zrok-build-debugging
Version: 0.0.10010
Summary: zrok
Home-page: https://github.com/openziti/zrok
Author: NetFoundry
Author-email: developers@openziti.org
License: Apache 2.0
Project-URL: Source, https://github.com/openziti/zrok
Project-URL: Tracker, https://github.com/openziti/zrok/issues
Project-URL: Discussion, https://openziti.discourse.group/
Keywords: zrok
Requires-Python: >3.10.0
Requires-Dist: openziti>=1.0.0
Requires-Dist: urllib3>=2.1.0
Dynamic: description
Dynamic: keywords
Dynamic: requires-dist
Dynamic: requires-python
Dynamic: summary
